{"operator": {"id": "monthly_uvb_flux", "description": "月 UV-B 下行通量，健康风险和晴空辐射背景", "category": "monthly_surface_energy", "inputs": [], "expression": "duvb", "dag": {"op": "var", "name": "duvb"}, "output_unit": "W m-2", "source": "DS1", "co_occurs_with": ["monthly_uvb_clear_ratio"], "availability": {"effective_days": 365, "total_days": 365, "coverage_pct": 100.0}, "limitations": null}, "chain": {"indicators": ["monthly_uvb_flux"], "sources": ["DS1"], "edges": []}, "co_occurring": ["monthly_uvb_clear_ratio"]}