{"operator": {"id": "monthly_precip_total", "description": "月累计总降水，来自 DS1 MONTH_ACC", "category": "monthly_surface_energy", "inputs": [], "expression": "tp (MONTH_ACC)", "dag": {"op": "var", "name": "tp"}, "output_unit": "mm", "source": "DS1", "co_occurs_with": ["monthly_precip_mmday", "monthly_convective_precip", "monthly_large_scale_precip"], "availability": {"effective_days": 365, "total_days": 365, "coverage_pct": 100.0}, "limitations": "月背景，不反映逐日变化"}, "chain": {"indicators": ["monthly_precip_total"], "sources": ["DS1"], "edges": []}, "co_occurring": ["monthly_convective_precip", "monthly_large_scale_precip", "monthly_precip_mmday"]}